echolex.py
echolex-1.0.0.dist-info/licenses/LICENSE
echolex-1.0.0.dist-info/METADATA
echolex-1.0.0.dist-info/WHEEL
echolex-1.0.0.dist-info/entry_points.txt
echolex-1.0.0.dist-info/top_level.txt
echolex-1.0.0.dist-info/RECORD
