Metadata-Version: 2.4
Name: echolex
Version: 1.0.0
Summary: A CLI tool for audio transcription using OpenAI's Whisper model
Home-page: https://github.com/ramonfigueiredo/echolex
Author: Ramon Figueiredo
Author-email: Ramon Figueiredo <ramon.fgrd@gmail.com>
License: Apache-2.0
Project-URL: Homepage, https://github.com/ramonfigueiredo/echolex
Project-URL: Documentation, https://github.com/ramonfigueiredo/echolex#readme
Project-URL: Repository, https://github.com/ramonfigueiredo/echolex
Project-URL: Issues, https://github.com/ramonfigueiredo/echolex/issues
Keywords: whisper,audio,transcription,speech-to-text,stt,openai,ai,cli
Classifier: Development Status :: 4 - Beta
Classifier: Intended Audience :: Developers
Classifier: Intended Audience :: Science/Research
Classifier: License :: OSI Approved :: Apache Software License
Classifier: Operating System :: OS Independent
Classifier: Programming Language :: Python :: 3
Classifier: Programming Language :: Python :: 3.8
Classifier: Programming Language :: Python :: 3.9
Classifier: Programming Language :: Python :: 3.10
Classifier: Programming Language :: Python :: 3.11
Classifier: Programming Language :: Python :: 3.12
Classifier: Topic :: Multimedia :: Sound/Audio :: Speech
Classifier: Topic :: Scientific/Engineering :: Artificial Intelligence
Requires-Python: >=3.8
License-File: LICENSE
Requires-Dist: openai-whisper
Requires-Dist: ffmpeg-python>=0.2.0
Requires-Dist: certifi
Requires-Dist: torch>=2.0.0
Requires-Dist: tqdm
Requires-Dist: numpy>=1.26.0
Provides-Extra: dev
Requires-Dist: pytest>=7.0.0; extra == "dev"
Requires-Dist: pytest-cov>=4.0.0; extra == "dev"
Requires-Dist: black>=23.0.0; extra == "dev"
Requires-Dist: flake8>=6.0.0; extra == "dev"
Dynamic: author
Dynamic: home-page
Dynamic: license-file
Dynamic: requires-python
